elements_manager/Compare_Xpath.py
elements_manager/FindElements.py
elements_manager/FindXpath.py
elements_manager/MatchAttributes.py
elements_manager/__init__.py
elements_manager-1.0.2.dist-info/LICENSE
elements_manager-1.0.2.dist-info/METADATA
elements_manager-1.0.2.dist-info/WHEEL
elements_manager-1.0.2.dist-info/top_level.txt
elements_manager-1.0.2.dist-info/RECORD
