Metadata-Version: 2.1
Name: elements-manager
Version: 1.0.2
Summary: Selenium Element Finder Library
Home-page: UNKNOWN
Author: Shrikar
Author-email: datakund@gmail.com
License: Apache License 2.0
Keywords: selenium no-html web-scraping bots test-automation no-code low-code cloud proxy datakund element-manager selenium element manager
Platform: UNKNOWN
Requires-Dist: requests
Requires-Dist: beautifulsoup4
